MANIFEST.in
setup.cfg
setup.py
gerritpy/__init__.py
gerritpy.egg-info/PKG-INFO
gerritpy.egg-info/SOURCES.txt
gerritpy.egg-info/dependency_links.txt
gerritpy.egg-info/requires.txt
gerritpy.egg-info/top_level.txt