Metadata-Version: 1.0
Name: gerritpy
Version: 0.0.1
Summary: a library for gerrit rest api
Home-page: https://github.com/diaojunxian/gerritPython
Author: diaojunxian
Author-email: diaojunxian@huami.com
License: MIT License
Keywords: gerrit py
Platform: any
